advent_of_code_data-2.2.0.dist-info/licenses/LICENSE
aocd/__init__.py
aocd/_ipykernel.py
aocd/cli.py
aocd/cookies.py
aocd/examples.py
aocd/exceptions.py
aocd/get.py
aocd/models.py
aocd/post.py
aocd/py.typed
aocd/runner.py
aocd/types.py
aocd/utils.py
advent_of_code_data-2.2.0.dist-info/METADATA
advent_of_code_data-2.2.0.dist-info/WHEEL
advent_of_code_data-2.2.0.dist-info/entry_points.txt
advent_of_code_data-2.2.0.dist-info/top_level.txt
advent_of_code_data-2.2.0.dist-info/RECORD
