Metadata-Version: 2.4
Name: advent-of-code-data
Version: 2.2.0
Summary: Get your puzzle data with a single import
Author-email: Wim Jeantine-Glenn <hey@wimglenn.com>
License-Expression: MIT
Project-URL: Homepage, https://github.com/wimglenn/advent-of-code-data
Classifier: Intended Audience :: Developers
Classifier: Programming Language :: Python :: 3
Classifier: Topic :: Software Development :: Libraries
Classifier: Topic :: Games/Entertainment :: Puzzle Games
Requires-Python: >=3.10
License-File: LICENSE
Requires-Dist: beautifulsoup4
Requires-Dist: pebble
Requires-Dist: urllib3
Requires-Dist: tzdata; platform_system == "Windows"
Requires-Dist: aocd-example-parser>=2025.12.12
Requires-Dist: typing_extensions; python_version < "3.11"
Provides-Extra: nb
Requires-Dist: IPython; extra == "nb"
Requires-Dist: jupyter-server; extra == "nb"
Dynamic: license-file
